sqs_list_filled_queues.py
sqs_list_filled_queues-0.2.dist-info/licenses/LICENSE
sqs_list_filled_queues-0.2.dist-info/METADATA
sqs_list_filled_queues-0.2.dist-info/WHEEL
sqs_list_filled_queues-0.2.dist-info/entry_points.txt
sqs_list_filled_queues-0.2.dist-info/top_level.txt
sqs_list_filled_queues-0.2.dist-info/RECORD
