Metadata-Version: 2.4
Name: sqs-list-filled-queues
Version: 0.2
Summary: A Python script to monitor and list Amazon SQS queues with messages, featuring real-time updates and AWS console links.
Home-page: https://github.com/baztian/sqs-list-filled-queues
Classifier: Programming Language :: Python :: 3
Classifier: License :: OSI Approved :: MIT License
Classifier: Operating System :: OS Independent
License-File: LICENSE
Requires-Dist: boto3
Dynamic: classifier
Dynamic: description
Dynamic: description-content-type
Dynamic: home-page
Dynamic: license-file
Dynamic: requires-dist
Dynamic: summary
